smplcodec/__init__.py
smplcodec/codec.py
smplcodec/constants.py
smplcodec/mcs.py
smplcodec/utils.py
smplcodec/version.py
smplcodec-2.3.0.dist-info/METADATA
smplcodec-2.3.0.dist-info/WHEEL
smplcodec-2.3.0.dist-info/RECORD
