Metadata-Version: 2.3
Name: smplcodec
Version: 2.3.0
Summary: A library to read and write .smpl avatar files
License: MIT
Author: Talha Zaman
Author-email: talha@meshcapade.com
Requires-Python: >=3.11
Classifier: License :: OSI Approved :: MIT License
Classifier: Programming Language :: Python :: 3
Classifier: Programming Language :: Python :: 3.11
Classifier: Programming Language :: Python :: 3.12
Classifier: Programming Language :: Python :: 3.13
Requires-Dist: numpy (>=1.24)
Requires-Dist: scipy (>=1.16.1,<2.0.0)
Requires-Dist: semver (>=3.0)
Requires-Dist: tomli (>=2.0)
